<annotation>
	<folder>New folder</folder>
	<filename>PV Rajashekar Invoice JAN 26- 29 Feb 2020-page7_Figure_1-5.png</filename>
	<path>D:\PycharmCode\Data_Creation\Augmented_Images\02\New folder\PV Rajashekar Invoice JAN 26- 29 Feb 2020-page7_Figure_1-5.png</path>
	<source>
		<database>Unknown</database>
	</source>
	<size>
		<width>150</width>
		<height>106</height>
		<depth>3</depth>
	</size>
	<segmented>0</segmented>
	<object>
		<name>bryteside</name>
		<pose>Unspecified</pose>
		<truncated>0</truncated>
		<difficult>0</difficult>
		<bndbox>
			<xmin>66</xmin>
			<ymin>24</ymin>
			<xmax>140</xmax>
			<ymax>85</ymax>
		</bndbox>
	</object>
</annotation>
